agenticx/__init__.py
agenticx/agents/__init__.py
agenticx/agents/mining_graph.py
agenticx/agents/mining_planner_agent.py
agenticx/agents/spawn_worker.py
agenticx/cli/__init__.py
agenticx/cli/client.py
agenticx/cli/debug.py
agenticx/cli/deploy.py
agenticx/cli/docs.py
agenticx/cli/env_template.txt
agenticx/cli/main.py
agenticx/cli/scaffold.py
agenticx/cli/tools.py
agenticx/collaboration/__init__.py
agenticx/collaboration/base.py
agenticx/collaboration/config.py
agenticx/collaboration/delegation.py
agenticx/collaboration/enums.py
agenticx/collaboration/manager.py
agenticx/collaboration/memory.py
agenticx/collaboration/metrics.py
agenticx/collaboration/patterns.py
agenticx/collaboration/intelligence/__init__.py
agenticx/collaboration/intelligence/collaboration_intelligence.py
agenticx/collaboration/intelligence/message_router.py
agenticx/collaboration/intelligence/models.py
agenticx/collaboration/intelligence/role_assigner.py
agenticx/configs/knowledge_graphers_config.yml
agenticx/core/__init__.py
agenticx/core/adapters.py
agenticx/core/agent.py
agenticx/core/agent_executor.py
agenticx/core/background.py
agenticx/core/code_action_executor.py
agenticx/core/communication.py
agenticx/core/component.py
agenticx/core/context_compiler.py
agenticx/core/discovery.py
agenticx/core/error_handler.py
agenticx/core/event.py
agenticx/core/event_bus.py
agenticx/core/executor.py
agenticx/core/graph.py
agenticx/core/interruption.py
agenticx/core/marketplace.py
agenticx/core/message.py
agenticx/core/performance.py
agenticx/core/plan_notebook.py
agenticx/core/plan_storage.py
agenticx/core/platform.py
agenticx/core/prompt.py
agenticx/core/registry.py
agenticx/core/security.py
agenticx/core/slave_parallel_executor.py
agenticx/core/task.py
agenticx/core/task_validator.py
agenticx/core/token_counter.py
agenticx/core/tool.py
agenticx/core/tool_system.py
agenticx/core/tool_v2.py
agenticx/core/workflow.py
agenticx/core/workflow_engine.py
agenticx/deploy/__init__.py
agenticx/deploy/base.py
agenticx-0.2.0.dist-info/licenses/LICENSE
agenticx-0.2.0.dist-info/METADATA
agenticx-0.2.0.dist-info/WHEEL
agenticx-0.2.0.dist-info/entry_points.txt
agenticx-0.2.0.dist-info/top_level.txt
agenticx-0.2.0.dist-info/RECORD
