Metadata-Version: 2.4
Name: agenticx
Version: 0.2.0
Summary: A unified, scalable, production-ready multi-agent application development framework
Author-email: Ziran Li <bingzhenli@hotmail.com>
License: AGPL-3.0
Project-URL: Homepage, https://github.com/DemonDamon/AgenticX
Project-URL: Documentation, https://agenticx.ai/docs
Project-URL: Repository, https://github.com/DemonDamon/AgenticX
Project-URL: Issues, https://github.com/DemonDamon/AgenticX/issues
Project-URL: Discussions, https://github.com/DemonDamon/AgenticX/discussions
Keywords: ai,agents,multi-agent,framework,automation,llm,workflow,orchestration
Classifier: Development Status :: 4 - Beta
Classifier: Intended Audience :: Developers
Classifier: License :: OSI Approved :: GNU Affero General Public License v3
Classifier: Operating System :: OS Independent
Classifier: Programming Language :: Python :: 3
Classifier: Programming Language :: Python :: 3.8
Classifier: Programming Language :: Python :: 3.9
Classifier: Programming Language :: Python :: 3.10
Classifier: Programming Language :: Python :: 3.11
Classifier: Programming Language :: Python :: 3.12
Classifier: Topic :: Software Development :: Libraries :: Python Modules
Classifier: Topic :: Scientific/Engineering :: Artificial Intelligence
Classifier: Topic :: Internet :: WWW/HTTP :: Dynamic Content
Classifier: Topic :: System :: Distributed Computing
Requires-Python: >=3.8
License-File: LICENSE
Requires-Dist: pydantic>=2.0.0
Requires-Dist: typing-extensions>=4.0.0
Requires-Dist: loguru>=0.7.0
Requires-Dist: rich>=13.0.0
Requires-Dist: click>=8.0.0
Requires-Dist: PyYAML>=6.0
Requires-Dist: jinja2>=3.0.0
Requires-Dist: python-dotenv>=1.0.0
Requires-Dist: httpx>=0.25.0
Requires-Dist: requests>=2.31.0
Requires-Dist: aiohttp>=3.9.0
Requires-Dist: aiofiles>=23.0.0
Requires-Dist: websockets>=12.0
Requires-Dist: fastapi>=0.100.0
Requires-Dist: uvicorn>=0.23.0
Requires-Dist: typer>=0.9.0
Requires-Dist: cryptography>=41.0.0
Requires-Dist: psycopg2-binary>=2.9.0
Requires-Dist: chardet>=5.0.0
Requires-Dist: docstring-parser<0.12,>=0.11
Requires-Dist: SQLAlchemy>=2.0.0
Requires-Dist: ujson>=5.8.0
Requires-Dist: tqdm>=4.65.0
Requires-Dist: joblib>=1.3.0
Requires-Dist: openai>=1.50.0
Requires-Dist: litellm>=1.50.0
Requires-Dist: tiktoken>=0.7.0
Requires-Dist: tokenizers>=0.19.0
Requires-Dist: huggingface-hub>=0.24.0
Requires-Dist: mem0ai>=0.1.0
Requires-Dist: redis>=5.0.0
Requires-Dist: pymilvus>=2.4.0
Requires-Dist: anthropic>=0.40.0
Requires-Dist: ollama>=0.3.0
Requires-Dist: chromadb>=0.5.0
Requires-Dist: qdrant-client>=1.10.0
Requires-Dist: prometheus-client>=0.17.0
Requires-Dist: opentelemetry-api>=1.20.0
Requires-Dist: opentelemetry-sdk>=1.20.0
Requires-Dist: pandas>=2.0.0
Requires-Dist: numpy>=1.24.0
Requires-Dist: scikit-learn>=1.3.0
Requires-Dist: scipy>=1.11.0
Requires-Dist: matplotlib>=3.7.0
Requires-Dist: seaborn>=0.12.0
Requires-Dist: plotly>=5.15.0
Requires-Dist: asyncio-mqtt>=0.16.0
Requires-Dist: mcp>=1.0.0
Requires-Dist: PyMuPDF>=1.23.0
Requires-Dist: pypdf>=3.15.0
Requires-Dist: PyPDF2>=3.0.0
Requires-Dist: python-docx>=0.8.11
Requires-Dist: python-pptx>=0.6.21
Requires-Dist: docx2txt>=0.8
Requires-Dist: pytesseract>=0.3.10
Requires-Dist: pdf2image>=1.16.0
Requires-Dist: easyocr>=1.7.0
Requires-Dist: python-Levenshtein>=0.21.0
Requires-Dist: RapidFuzz>=3.0.0
Requires-Dist: networkx>=3.1
Requires-Dist: cdlib>=0.3.0
Requires-Dist: wurlitzer>=3.0.0
Requires-Dist: bayanpy>=0.0.6
Requires-Dist: infomap>=2.7.0
Requires-Dist: neo4j>=5.12.0
Requires-Dist: pyclustering>=0.10.0
Requires-Dist: ASLPAw>=2.1.0
Requires-Dist: leidenalg>=0.10.0
Requires-Dist: mkdocs>=1.5.0
Requires-Dist: mkdocs-material>=9.0.0
Requires-Dist: pydoc-markdown>=4.8.0
Requires-Dist: psutil>=5.9.0
Requires-Dist: structlog>=23.1.0
Provides-Extra: dev
Requires-Dist: pytest>=7.4.0; extra == "dev"
Requires-Dist: pytest-asyncio>=0.21.0; extra == "dev"
Requires-Dist: pytest-cov>=4.0.0; extra == "dev"
Requires-Dist: black>=23.0.0; extra == "dev"
Requires-Dist: isort>=5.12.0; extra == "dev"
Requires-Dist: flake8>=6.0.0; extra == "dev"
Requires-Dist: mypy>=1.0.0; extra == "dev"
Requires-Dist: pre-commit>=3.0.0; extra == "dev"
Provides-Extra: docs
Requires-Dist: mkdocs>=1.5.0; extra == "docs"
Requires-Dist: mkdocs-material>=9.0.0; extra == "docs"
Requires-Dist: mkdocstrings>=0.22.0; extra == "docs"
Requires-Dist: mkdocs-autorefs>=0.4.0; extra == "docs"
Requires-Dist: pydoc-markdown>=4.8.0; extra == "docs"
Provides-Extra: all
Requires-Dist: agenticx[dev,docs]; extra == "all"
Dynamic: license-file
